llm_offset/__init__.py
llm_offset/interceptor.py
llm_offset/main.py
llm_offset-0.8.0.dist-info/METADATA
llm_offset-0.8.0.dist-info/WHEEL
llm_offset-0.8.0.dist-info/top_level.txt
llm_offset-0.8.0.dist-info/RECORD
