Metadata-Version: 2.1
Name: llm-offset
Version: 0.8.0
Requires-Dist: openai
